sales/__init__.py
sales/tools/__init__.py
sales/tools/sales_api_tool.py
sales/tools/utils.py
sales/yamls/sales_api_tool.yaml
tests/__init__.py
tests/test_sales_api_tool.py
sales_intelligence_flow-0.0.3.dist-info/METADATA
sales_intelligence_flow-0.0.3.dist-info/WHEEL
sales_intelligence_flow-0.0.3.dist-info/entry_points.txt
sales_intelligence_flow-0.0.3.dist-info/top_level.txt
sales_intelligence_flow-0.0.3.dist-info/RECORD
