Metadata-Version: 2.1
Name: sales_intelligence_flow
Version: 0.0.3
Summary: This is Sales Intelligence prompt flow
